stlearn/__init__.py
stlearn/__main__.py
stlearn/_settings.py
stlearn/add.py
stlearn/classes.py
stlearn/datasets.py
stlearn/em.py
stlearn/gui.py
stlearn/logging.py
stlearn/pp.py
stlearn/types.py
stlearn/utils.py
stlearn/_datasets/__init__.py
stlearn/_datasets/_datasets.py
stlearn/adds/__init__.py
stlearn/adds/add_deconvolution.py
stlearn/adds/add_image.py
stlearn/adds/add_labels.py
stlearn/adds/add_loupe_clusters.py
stlearn/adds/add_lr.py
stlearn/adds/add_mask.py
stlearn/adds/add_positions.py
stlearn/adds/annotation.py
stlearn/adds/parsing.py
stlearn/app/__init__.py
stlearn/app/app.py
stlearn/app/cli.py
stlearn/app/requirements.txt
stlearn/app/source/__init__.py
stlearn/app/source/readme.md
stlearn/app/source/forms/__init__.py
stlearn/app/source/forms/form_validators.py
stlearn/app/source/forms/forms.py
stlearn/app/source/forms/helper_functions.py
stlearn/app/source/forms/utils.py
stlearn/app/source/forms/view_helpers.py
stlearn/app/source/forms/views.py
stlearn/app/static/css/material-dashboard.min.css
stlearn/app/static/css/style.css
stlearn/app/static/img/Settings.gif
stlearn/app/static/img/favicon.png
stlearn/app/static/img/loading_gif.gif
stlearn/app/static/js/core/bootstrap-material-design.min.js
stlearn/app/static/js/core/jquery.min.js
stlearn/app/static/js/core/popper.min.js
stlearn/app/static/js/plugins/perfect-scrollbar.jquery.min.js
stlearn/app/templates/__init__.py
stlearn/app/templates/annotate_plot.html
stlearn/app/templates/base.html
stlearn/app/templates/cci.html
stlearn/app/templates/cci_old.html
stlearn/app/templates/cci_plot.html
stlearn/app/templates/choose_cluster.html
stlearn/app/templates/cluster_plot.html
stlearn/app/templates/clustering.html
stlearn/app/templates/dea.html
stlearn/app/templates/flash_header.html
stlearn/app/templates/gene_plot.html
stlearn/app/templates/index.html
stlearn/app/templates/lr.html
stlearn/app/templates/lr_plot.html
stlearn/app/templates/preprocessing.html
stlearn/app/templates/progress.html
stlearn-1.2.2.dist-info/licenses/AUTHORS.rst
stlearn-1.2.2.dist-info/licenses/LICENSE
stlearn-1.2.2.dist-info/METADATA
stlearn-1.2.2.dist-info/WHEEL
stlearn-1.2.2.dist-info/entry_points.txt
stlearn-1.2.2.dist-info/top_level.txt
stlearn-1.2.2.dist-info/RECORD
