Metadata-Version: 2.4
Name: stlearn
Version: 1.2.2
Summary: A downstream analysis toolkit for Spatial Transcriptomic data
Author-email: Genomics and Machine Learning lab <andrew.newman@uq.edu.au>
License: BSD license
Project-URL: Homepage, https://github.com/BiomedicalMachineLearning/stLearn
Project-URL: Repository, https://github.com/BiomedicalMachineLearning/stLearn
Keywords: stlearn
Classifier: Development Status :: 5 - Production/Stable
Classifier: Intended Audience :: Developers
Classifier: License :: OSI Approved :: BSD License
Classifier: Natural Language :: English
Classifier: Programming Language :: Python :: 3.10
Classifier: Programming Language :: Python :: 3.11
Classifier: Programming Language :: Python :: 3.12
Requires-Python: <3.13,>=3.10
License-File: LICENSE
License-File: AUTHORS.rst
Requires-Dist: bokeh<4.0,>=3.7.0
Requires-Dist: click<9.0,>=8.2.0
Requires-Dist: leidenalg<0.11,>=0.10.0
Requires-Dist: louvain>=0.8.2
Requires-Dist: numba>=0.58.1
Requires-Dist: numpy<2.0,>=1.26.0
Requires-Dist: pillow<12.0,>=11.0.0
Requires-Dist: scanpy<2.0,>=1.11.0
Requires-Dist: scikit-image<0.23,>=0.22.0
Requires-Dist: tensorflow>=2.14.1
Requires-Dist: keras>=2.14.0
Requires-Dist: pandas>=2.3.0
Requires-Dist: imageio<3.0,>=2.37.0
Requires-Dist: scipy<2.0,>=1.11.0
Requires-Dist: scikit-learn<2.0,>=1.7.0
Provides-Extra: dev
Requires-Dist: black>=23.0; extra == "dev"
Requires-Dist: ruff>=0.1.0; extra == "dev"
Requires-Dist: mypy>=1.16; extra == "dev"
Requires-Dist: pytest>=7.0; extra == "dev"
Requires-Dist: tox>=4.0; extra == "dev"
Requires-Dist: ghp-import>=2.1.0; extra == "dev"
Requires-Dist: sphinx>=4.0; extra == "dev"
Requires-Dist: furo==2024.8.6; extra == "dev"
Requires-Dist: myst-parser>=0.18; extra == "dev"
Requires-Dist: nbsphinx>=0.9.0; extra == "dev"
Requires-Dist: types-tensorflow>=2.8.0; extra == "dev"
Requires-Dist: sphinx-autodoc-typehints>=1.24.0; extra == "dev"
Requires-Dist: sphinx-autosummary-accessors>=2023.4.0; extra == "dev"
Provides-Extra: test
Requires-Dist: pytest; extra == "test"
Requires-Dist: pytest-cov; extra == "test"
Provides-Extra: webapp
Requires-Dist: flask>=2.0.0; extra == "webapp"
Requires-Dist: flask-wtf>=1.0.0; extra == "webapp"
Requires-Dist: wtforms>=3.0.0; extra == "webapp"
Requires-Dist: markupsafe>2.1.0; extra == "webapp"
Provides-Extra: jupyter
Requires-Dist: jupyter>=1.0.0; extra == "jupyter"
Requires-Dist: jupyterlab>=3.0.0; extra == "jupyter"
Requires-Dist: ipywidgets>=7.6.0; extra == "jupyter"
Requires-Dist: plotly>=5.0.0; extra == "jupyter"
Requires-Dist: bokeh>=2.4.0; extra == "jupyter"
Requires-Dist: rpy2>=3.4.0; extra == "jupyter"
Dynamic: license-file
